{"id": "849a51f46c1d06cdecb9012bd6948e4a1e902920a95e7db3e9b15d49ce6bd59b", "kind": "simulation", "lineage": {"node": "ElasticConstants", "material": "Si (diamond)", "conditions": {"T": "300 K", "method": "PIMD+TDEP", "component": "C11"}, "values": {"value": 133.6, "units": "GPa"}, "source": "paper:quantum-elastic-2024-folkner"}, "source": {"kind": "simulation", "ref": "paper:quantum-elastic-2024-folkner", "detail": "\"300 133.6 59.4 64.3 84.1 153.7 134.1 97.0 53.4\" (table, p. 19). Elastic moduli and thermal conductivity of quantum materials at finite temperature (Folkner, Barbalinardo et al.), 2024"}}